insight_client/__init__.py
insight_client/client.py
insight_client/config.py
insight_client/file.py
insight_client-0.3.6.dist-info/LICENSE
insight_client-0.3.6.dist-info/METADATA
insight_client-0.3.6.dist-info/WHEEL
insight_client-0.3.6.dist-info/entry_points.txt
insight_client-0.3.6.dist-info/RECORD
