Metadata-Version: 2.1
Name: insight-client
Version: 0.3.6
Summary: Python client and CLI for the insight system
Author: Johan
Author-email: johan@resolve.works
Requires-Python: >=3.11,<4.0
Classifier: Programming Language :: Python :: 3
Classifier: Programming Language :: Python :: 3.11
Classifier: Programming Language :: Python :: 3.12
Classifier: Programming Language :: Python :: 3.13
Requires-Dist: click (>=8.1.7,<9.0.0)
Requires-Dist: keyring (>=25.5.0,<26.0.0)
Requires-Dist: minio (>=7.2.0,<8.0.0)
Requires-Dist: requests-oauthlib (>=2.0.0,<3.0.0)
Requires-Dist: tqdm (>=4.66.1,<5.0.0)
